sentry_crashpad.libs/libstdc++-0530927c.so.6.0.32
sentry_crashpad.libs/libgcc_s-1257a076.so.1
sentry_crashpad/__init__.py
sentry_crashpad/data/bin/crashpad_handler
sentry_crashpad-0.7.17.1.dist-info/WHEEL
sentry_crashpad-0.7.17.1.dist-info/RECORD
sentry_crashpad-0.7.17.1.dist-info/entry_points.txt
sentry_crashpad-0.7.17.1.dist-info/METADATA
sentry_crashpad-0.7.17.1.dist-info/licenses/LICENSE
