Metadata-Version: 2.2
Name: sentry-crashpad
Version: 0.7.17.1
Summary: Crashpad is an open-source multiplatform crash reporting system written in C++ by Google.
Author-Email: Vincent <magicdroidx@gmail.com>
License: 
Classifier: Programming Language :: C
Classifier: Programming Language :: C++
Classifier: Operating System :: OS Independent
Classifier: License :: OSI Approved :: MIT License
Classifier: Intended Audience :: Developers
Classifier: Topic :: Software Development :: Quality Assurance
Project-URL: Documentation, https://docs.sentry.io/platforms/native/configuration/backends/crashpad/
Project-URL: Download, https://github.com/getsentry/sentry-native/releases
Project-URL: Source, https://github.com/EndstoneMC/sentry-crashpad
